bioscons/__init__.py
bioscons/fast.py
bioscons/fileutils.py
bioscons/slurm.py
bioscons/utils.py
bioscons/data/ver
bioscons-0.9.0.dist-info/DESCRIPTION.rst
bioscons-0.9.0.dist-info/METADATA
bioscons-0.9.0.dist-info/RECORD
bioscons-0.9.0.dist-info/WHEEL
bioscons-0.9.0.dist-info/metadata.json
bioscons-0.9.0.dist-info/top_level.txt
