Metadata-Version: 2.0
Name: bioscons
Version: 0.9.0
Summary: Extends the scons build tool for reproducible research in bioinformatics.
Home-page: http://github.com/nhoffman/bioscons
Author: Noah Hoffman
Author-email: noah.hoffman@gmail.com
License: UNKNOWN
Download-URL: http://pypi.python.org/pypi/bioscons
Platform: UNKNOWN
Requires-Dist: scons (>=2.4.0)
